nonebot_plugin_areusleepy-0.1.8.dist-info/METADATA
nonebot_plugin_areusleepy-0.1.8.dist-info/WHEEL
nonebot_plugin_areusleepy-0.1.8.dist-info/entry_points.txt
nonebot_plugin_areusleepy-0.1.8.dist-info/licenses/LICENSE
nonebot_plugin_areusleepy/__init__.py
nonebot_plugin_areusleepy/__main__.py
nonebot_plugin_areusleepy/config.py
nonebot_plugin_areusleepy-0.1.8.dist-info/RECORD
