Metadata-Version: 2.1
Name: nonebot-plugin-areusleepy
Version: 0.1.8
Summary: Let bot look!!!
Author-Email: Murasame <congyu@sbhfy.cn>, wyf9 <wyf9@wyf9.top>
License: MIT
Project-URL: homepage, https://github.com/Murasame-Dev/nonebot-plugin-areusleepy
Requires-Python: <4.0,>=3.9
Requires-Dist: nonebot2[httpx]>=2.4.2
Requires-Dist: nonebot-plugin-apscheduler>=0.3.0
Requires-Dist: nonebot-plugin-alconna>=0.12.0
